hounaartoolkit/__init__.py
hounaartoolkit/analyzer.py
hounaartoolkit/crypt.py
hounaartoolkit/netscanner.py
hounaartoolkit/rootkit.py
hounaartoolkit/type_rover.py
hounaartoolkit/youtub.py
HounaarToolkit-0.1.2.dist-info/METADATA
HounaarToolkit-0.1.2.dist-info/WHEEL
HounaarToolkit-0.1.2.dist-info/entry_points.txt
HounaarToolkit-0.1.2.dist-info/top_level.txt
HounaarToolkit-0.1.2.dist-info/RECORD
